{
    "height": "2.9 in.",
    "displaytype": "LCD",
    "opticalzoom": "7.1x",
    "maxvideoresolution": "1920 x 1080",
    "category": "camera",
    "digitalzoom": "4x",
    "width": "4.7 in.",
    "type": "Point & ShootUPC:018208131815",
    "focallengthequivalentto35mmcamera": "28 - 200 mm",
    "mpn": "26360Screen Size:3\"",
    "brand": "NikonMegapixels:12.2 MP",
    "sensortype": "CMOS",
    "screensize": "3\"",
    "wevemadeafewchangestobidding": "Were these helpful?",
    "cameratype": "Point & Shoot",
    "upc": "018208131815, 018208263608",
    "displaysize": "3\"",
    "depth": "2 in.",
    "sensorresolution": "12.2 MP",
    "supportedflashmemory": "SD Card, SD Memory Card, SDHC Card, SDHC Memory Card, SDXC Card, SDXC Memory Card",
    "model": "P7700Optical Zoom:7.1x"
}