{
    "modelname": "HT-INTB10",
    "weight": "3 lb",
    "height": "4.9\"",
    "connectivitytechnology": "Cable",
    "producttype": "Surveillance Camera",
    "illumination": "Minimum 0 Lux",
    "productseries": "2",
    "category": "camera",
    "productline": "Intensifier",
    "colorsupported": "Color",
    "width": "3.9\"",
    "focallength": "9 mm to 22 mm",
    "sensortype": "CCD",
    "brandname": "Speco",
    "compatibility": "NTSC",
    "manufacturer": "Speco Technologies",
    "opticalzoom": "2.4x",
    "productname": "Intensifier 2 Series HT-INTB10 Weatherproof Bullet Camera",
    "item": "680233",
    "depth": "8.2\"",
    "ecolabel": "RoHS"
}