{
    "weight": "6.17 Oz.",
    "flashtype": "Built-In",
    "height": "2.11 in.",
    "displaytype": "LCD",
    "cameraflashfeatures": "Auto Flash, Fill-in Flash, Flash Off, Red-eye Reduction Flash, Slow Sync",
    "additionalfeatures": "Not Interchangeable Lenses, USB 2.0, With Tripod Mount",
    "opticalzoom": "3x",
    "maxvideoresolution": "640 x 480",
    "category": "camera",
    "lightsensitivitymax": "100",
    "stillimageformat": "JPEG",
    "depth": "1.41 in.",
    "width": "4.61 in.",
    "mpn": "DSC-P93",
    "brand": "Sony",
    "sensortype": "CCD",
    "screensize": "1.5\"",
    "wevemadeafewchangestobidding": "Were these helpful?",
    "microphonetype": "With Built-in Microphone",
    "focusadjustment": "Autofocus & Manual Focus",
    "cameratype": "Point & Shoot",
    "displaysize": "1.5\"",
    "digitalzoom": "2x",
    "sensorresolution": "5.1 MP",
    "viewfindertype": "Optical",
    "supportedflashmemory": "Memory Stick, Memory Stick PRO",
    "model": "DSC-P93",
    "operatingsystemsupported": "Apple Mac OS 9, Apple Mac OS X, Microsoft Windows 2000, Microsoft Windows 98, Microsoft Windows 98SE, Microsoft Windows ME, Microsoft Windows XP Home Edition, Microsoft Windows XP Professional",
    "whitebalance": "Auto, Cloudy (Preset), Daylight / Sunny (Preset), Fluorescent (Preset), Incandescent (Preset)"
}