{
    "weight": "10.5 Oz.",
    "flashtype": "Built-in flash",
    "maxoperatingtemperature": "45 \u00c2\u00b0C",
    "height": "2.72 in.",
    "displaytype": "LCD",
    "opticalviewfindertype": "Real-image",
    "cameraflashfeatures": "Auto Flash, Fill-in Flash, Flash Off",
    "additionalfeatures": "Auto Power Save, DPOF Support, Not Interchangeable Lenses, USB 2.0 Compatibility, USB Compatibility, With Tripod Mount",
    "displaysize": "1.4\"",
    "maxvideoresolution": "288 x 208",
    "category": "camera",
    "displayrotation": "Built-in",
    "lightsensitivitymax": "100",
    "stillimageformat": "JPEG",
    "screendetails": "LCD display - TFT active matrix - 1.4\" - color",
    "lightsensitivity": "ISO 100",
    "sensorsize": "1/2\"",
    "width": "4.37 in.",
    "digitalzoom": "2x",
    "focallengthequivalentto35mmcamera": "42mm",
    "minshutterspeed": "1/15 sec",
    "batteryformfactor": "Standard form factor",
    "mpn": "Q2153A#122",
    "brand": "HP",
    "sensortype": "CMOS",
    "minoperatingtemperature": "5 \u00c2\u00b0C",
    "screensize": "1.4\"",
    "digitalvideoformat": "AVI, MJPEG",
    "wevemadeafewchangestobidding": "Were these helpful?",
    "microphonetype": "None",
    "integratedmemorysize": "4 MB",
    "expansionslot": "1 x CompactFlash Card, 1 x CompactFlash Card - type I",
    "focusadjustment": "Fixed Focus, Focus Free",
    "cameratype": "Point & Shoot",
    "shootingmodes": "Frame Movie Mode",
    "maxshutterspeed": "1/1000 sec",
    "exposuremodes": "Automatic",
    "upc": "0808736398145, 88698432419",
    "connectortypes": "1 x DC power input, 1 x USB",
    "flashmodes": "Auto Mode, Fill-in Mode, OFF mode",
    "depth": "1.75 in.",
    "sensorresolution": "1.0 MP",
    "viewfindertype": "Optical, Optical (Through-the-lens)",
    "supportedflashmemory": "CompactFlash, CompactFlash Card Type I",
    "model": "120",
    "operatingsystemsupported": "Apple Mac OS 9, Apple Mac OS X, Microsoft Windows 2000, Microsoft Windows 98, Microsoft Windows ME, Microsoft Windows XP",
    "whitebalance": "Automatic"
}