{
    "weight": "4.59 Oz.",
    "flashtype": "Built-In",
    "height": "2.22 in.",
    "displaytype": "LCD",
    "maxvideoresolution": "640 x 480",
    "category": "camera",
    "lightsensitivitymax": "1000",
    "digitalzoom": "2x",
    "width": "3.74 in.",
    "type": "Point & ShootUPC:027242703995",
    "touchscreen": "Yes",
    "brand": "SonyMegapixels:7.2 MP",
    "screensize": "3\"",
    "wevemadeafewchangestobidding": "Were these helpful?",
    "integratedmemorysize": "56 MB",
    "cameratype": "Point & Shoot",
    "upc": "027242703995",
    "displaysize": "3\"",
    "depth": "0.92 in.",
    "sensorresolution": "7.2 MP",
    "model": "DSC-T50Screen Size:3\""
}