{
    "pictbridge": "Yes, PictBridge 1.0",
    "audioformats": "Linear PCM",
    "metering": "Yes, Multi-Pattern, Center-Weighted, Average, Spot",
    "memorycardtype": "Compact Flash (Type I), SD / SDHC / SDXC UHS-I compliant",
    "lenstype": "Nikon F mount (with AF coupling and AF contacts)",
    "maximumshutterspeed": "1/8000 sec",
    "sensorsize": "Full frame (35.9 x 24 mm)",
    "batterytype": "Lithium-Ion EN-EL15 Rechargeable Battery",
    "manualfocus": "Yes",
    "videoformat": "MOV, H.264, MPEG-4",
    "category": "camera",
    "microphone": "Yes, Built-in Monaural",
    "macromode": "Yes",
    "dimensions": "146 (W) x 123 (H) x 82 (D) mm",
    "redeyereduction": "Yes",
    "seller": "ShippingPriceDetails",
    "selftimer": "Yes, 2 s, 5 s, 10 s, 20 s",
    "syncterminal": "Yes, 1/250 sec",
    "autofocus": "Yes, Phase Detect, Multi-Area, Selective Single Point, Tracking, Single, Continuous, Face Detection, Live View",
    "type": "SLR",
    "cameraresolution": "37 MP",
    "hdmi": "Yes, Type C Mini HDMI",
    "flashrange": "12 m",
    "isorating": "100 - 25600",
    "imagestablizer": "No",
    "whitebalancing": "Custom White Balance (5), White Balance Presets (12), Auto, Incandescent, Fluorescent, Direct Sunlight, Flash, Cloudy, Shade, Preset Manual can be stored), Color Temperature (2500 K 10000 K), All with Fine-tuning",
    "weight": "1000 g",
    "powersupply": "EH-5b AC Adapter, Requires EP-5B Power Connector",
    "sensortype": "CMOS",
    "imageformat": "NEF (RAW), JPEG, NEF (RAW) JPEG, DCF 2.0, DPOF, EXIF 2.3 ( Fine, Normal & Basic Quality )",
    "otherfocusfeatures": "Focal Length Multiplier (1x), No. of Focus Points (51)",
    "minimumshutterspeed": "30 sec",
    "usbcable": "Yes",
    "facedetection": "Yes",
    "externalflash": "Yes, Hot-shoe, Wireless plus sync connector",
    "tvout": "Yes, Audio Output",
    "supportedlanguages": "23",
    "dustreduction": "Yes, Image sensor cleaning, Image Dust Off reference data (requires optional Capture NX 2 software)",
    "flashmodes": "Auto, On, Off, Red-eye, Slow sync, Rear curtain, High-speed sync",
    "builtinflash": "Yes, Manual pop-up with button release and a Guide Number of 12/39, 12/39 with manual flash (m/ft, ISO 100, 20 C/68 F)",
    "upgradablememory": "Yes",
    "processor": "Expeed 3",
    "maxresolution": "7360 x 4912 Pixels",
    "imagedisplayresolution": "921K dots",
    "videoresolution": "1920 x 1080 pixels at 30 fps",
    "display": "3.2 inch TFT Color LCD with 170 degrees wide-viewing angle"
}