{
    "weightkg": "1.00",
    "imagestabilization": "Optical",
    "category": "camera",
    "batterylife": "250 Shot",
    "minimumfocusdistance": "200 mm",
    "itemcode": "DCC-5249B011AA",
    "maximumframerate": "30 fps",
    "dimensionswxhxd": "116.7 mm x 80.5 mm x 64.7 mm",
    "maximumvideoresolution": "1920 x 1080",
    "effectiveresolution": "14.3 Megapixel",
    "touchscreen": "No",
    "videoformats": "MOV, MPEG-4",
    "batterysize": "Proprietary Battery Size",
    "focallength": "15.10 mm to 60.40 mm",
    "memorycardsupport": "Secure Digital (SD) Card",
    "price": "\u00c2\u00a3364.95",
    "focusmodes": "Auto",
    "screensize": "7.6 cm (3\")",
    "colour": "Black",
    "opticalzoom": "4x",
    "item": "Canon Powershot G1X Camera Black 14MP 4xZoom 3.0LCD FHD 28mm",
    "digitalzoom": "4x",
    "components": "PERIPHERALSMONITORS & TV'SDIGITAL CAMERASNETWORKINGSOFTWARECONSUMABLESCABLESNOTEBOOK & TABLETSCOMPUTERS",
    "brandmodel": "Canon 5249B011AA"
}