{
    "attr": "$1.00",
    "producttypegeneral": "Digital camera - compact",
    "depthdimensionsweight": "0.9 in",
    "maxvideoresolutiongeneral": "1280 x 720",
    "batterytype": "Canon NB-11L",
    "weightdimensionsweight": "4 oz",
    "generalwarranty": "1 year  parts and labor",
    "opticalsensortypegeneral": "CCD",
    "minshutterspeedexposurewhitebalance": "15 sec",
    "minoperatingtemperatureenvironmentalparameters": "32 \u00b0F",
    "effectivesensorresolutiongeneral": "16,000,000 pixels",
    "enclosurecolorgeneral": "Silver",
    "minfocusdistancelenssystem": "0.4 in",
    "depthin": "0.87",
    "sensortype": "CCD",
    "imageprocessor": "DIGIC 4+",
    "condition": "New",
    "focallengthequivalentto35mmcameralenssystem": "28 - 224mm",
    "heightin": "2.14",
    "widthin": "3.75",
    "specialeffectsexposurewhitebalance": "Fisheye, Monochrome, Miniature, Toy camera, Super Vivid, Poster",
    "exposurecompensationexposurewhitebalance": "\u00b12 EV range, in 1/3 EV steps",
    "flashtype": "Built-in",
    "humidityrangeoperatingenvironmentalparameters": "10 - 90%",
    "additionalfeatures": "Red eye reduction",
    "effectiveflashrangecameraflash": "1.6 ft - 10 ft ( wide lens ) \u00a6 4.3 ft - 5 ft ( tele lens )",
    "category": "camera",
    "digitalzoomgeneral": "4 x",
    "totalpixelsgeneral": "16,600,000 pixels",
    "maxoperatingtemperatureenvironmentalparameters": "104 \u00b0F",
    "featurescameraflash": "AF illuminator",
    "howmanypointswilliearn": "?",
    "focusadjustmentlenssystem": "Automatic",
    "avinterfacesgeneral": "Composite video/audio",
    "attr3d": "No",
    "heightdimensionsweight": "2.1 in",
    "accord": "Yes",
    "whitebalancepresets": "Fluorescent, cloudy, tungsten light, daylight, fluorescent light (daylight)",
    "exposuremodesexposurewhitebalance": "Program, automatic",
    "microphoneoperationmodemicrophone": "Mono",
    "batterylifedetailsbattery": "Photo shooting - 230 shots \u00a6 Photo shooting - 310 shots ( ECO mode ) \u00a6 Playback - 4 hours",
    "macrofocusrangelenssystem": "0.4 in - 19.7 in",
    "imagestoragememorystorage": "JPEG 4608 x 3456 \u00a6 JPEG 4608 x 2592 \u00a6 JPEG 3264 x 2488 \u00a6 JPEG 2048 x 1536 \u00a6 JPEG 640 x 480",
    "shootingmodes": "Portrait mode, slow shutter, fireworks, low light, snow",
    "megapixels": "16",
    "exposuremeteringexposurewhitebalance": "Evaluative, center-weighted, spot",
    "shipping": "Choose from a larger selection of items shipped right to your home.",
    "iso": "100-1600",
    "featureslenssystem": "Built-in lens shield",
    "features": "720p HD Video",
    "color": "Silver/gray",
    "resolutiondisplay": "230,000 pixels",
    "facedetectiongeneral": "Face Detection AF/AE/FE/WB, Face Detection Self-timer",
    "widthdimensionsweight": "3.7 in",
    "size": "Compact",
    "videorecording": "Yes",
    "opticalzoomgeneral": "8 x",
    "itemweightlbs": "0.28",
    "typelenssystem": "8 x zoom lens - 5 - 40 mm - f/3.2-6.9",
    "zoomadjustmentlenssystem": "Motorized drive",
    "imagesensorsize": "1/2.3\"",
    "supportedmemorycards": "SD card",
    "aeafcontrolgeneral": "Face-priority AF",
    "typedisplay": "2.7\" LCD display",
    "outputtype": "USB 1.0",
    "value": "Points",
    "lcdscreensize": "2.7 to 2.9 in.",
    "itemprice": "PointsBonusValue",
    "connectortypeconnections": "1 x USB 2.0 \u00a6 1 x composite video/audio output",
    "whitebalanceexposurewhitebalance": "Custom, automatic, presets",
    "batterylifeshotspercharge": "310",
    "imagestabilization": "Yes",
    "digitalvideoformatgeneral": "H.264, MOV",
    "lightsensitivityexposurewhitebalance": "ISO auto, ISO 100-1600",
    "displayfeaturesdisplay": "Built-in",
    "accessoriesincluded": "Battery charger, wrist strap",
    "flashmodescameraflash": "Fill-in mode, slow synchro, auto mode, flash OFF mode, red-eye reduction",
    "sensorresolutiongeneral": "16.0 Megapixel",
    "additionalfeaturesadditionalfeatures": "Direct print, built-in speaker, auto power save, DPOF support, digital image rotation, camera orientation detection, PictBridge support, histogram display, AE lock, AF lock, resizing an image, i-Contrast (Intelligent Contrast Correction) sy",
    "continuousshootingspeed": "0.8 frames per second, 3.3 frames per second",
    "imagerecordingformatgeneral": "JPEG",
    "videocapturememorystorage": "H.264 - 1280 x 720 - 25 fps \u00a6 H.264 - 640 x 480 - 30 fps \u00a6 H.264 - 1280 x 720 - 5 fps - Miniature Effect \u00a6 H.264 - 1280 x 720 - 2.5 fps \u00a6 H.264 - 1280 x 720 - 1.25 fps \u00a6 H.264 - 640 x 480 - 6 fps \u00a6 H.264 - 640",
    "maximumscreenresolution": "230,000",
    "autofocusgeneral": "TTL contrast detection",
    "selftimerdelayadditionalfeatures": "10 sec, 2 sec, 30 sec, 20 sec, 0 - 15 sec, 25 sec",
    "opticalzoom": "9x or less",
    "productbundle": "No",
    "points": "Value",
    "viewfindertype": "LCD",
    "maxshutterspeedexposurewhitebalance": "1/2000 sec"
}