{
    "weight": "247 g",
    "isosensitivity": "ISO 100 - 6400",
    "interface": "- USB 2.0 - HDMI",
    "size": "1/2.3\"",
    "category": "camera",
    "dimensions": "65.9 x 111.5 x 31.2 mm (H x W x D)",
    "panoramamode": "Yes",
    "focallength": "4.5 - 18 mm",
    "pictbridgedirectprinting": "Yes",
    "maximumaperture": "f/2 - f/4.9",
    "minimumaperture": "f/2 - f/4.9",
    "type": "CMOS",
    "appavailable": "Yes - Olympus Image Share",
    "hardcopymanualsupplied": "Yes",
    "dustproof": "Yes",
    "softwareincluded": "Image Management software",
    "accessoriesincluded": "- LI-90B Lithium-ion battery - F-2AC AC adapter - CB-USB8 USB cable - Hand strap",
    "waterproof": "Yes - up to 15 m",
    "attr35mmequivalent": "25 - 100 mm",
    "freezeproof": "Yes - up to -10\u00b0C",
    "effects": "Magic filters: Pop Art, Soft Focus, Pale & Light Colour, Grainy Film, Pin Hole, Diorama, Dramatic Tone",
    "imagestabiliser": "- Optical - Digital",
    "focusing": "Autofocus",
    "otherfeatures": "Crushproof up to 100 kg",
    "tvoutput": "- PAL - NTSC",
    "minimumdistance": "1 cm",
    "benefits": "Care Plan",
    "manufacturersguarantee": "2 years",
    "colour": "Black",
    "wifi": "Yes",
    "exposuremodes": "Exposure modes: Advanced Face Detection Technology, Shadow Adjustment Technology, Modes i-Auto, Programme automatic, Super Macro, Scene Modes, Aperture priority, Art Filter, Photo Story,Custom shooting, Panorama, Movie. Scene modes: Portrait, e-Portrait, Landscape, Interval shooting, Hand-held Starlight, Night Scene, Night Scene with portrait, Sports, Indoor, Self-portrait, Sunset, Fireworks, Cuisine, Documents, Beach and Snow, Underwater Snapshot, Underwater Wide 1, Underwater Wide 2, Underwater Macro, Snow, Panorama, Backlight HDR",
    "shockproof": "Yes - up to 2.1 m",
    "gps": "Yes",
    "resolution": "16 megapixels",
    "whitebalance": "- Auto WB system - Preset values: Overcast, Sunlight, Tungsten, Underwater, Flourescent 1 - One-touch white balance"
}