{
    "category": "camera",
    "code": "Please enter the security code as they are shown in the image right",
    "from": "Please enter the email. Please enter your correct business Email.",
    "deliverytime": "2-3Days",
    "supplyability": "10000 Piece/Pieces per Day",
    "modelnumber": "For Sony W5/W7",
    "placeoforigin": "Guangdong, China (Mainland)",
    "topic": "Your message's topic must be 1-150 characters in length.",
    "to": "Shenzhen Jonlin Digital Trading Co., Ltd",
    "paymentterms": "T/T,Western Union",
    "minimumorderquantity": "100 Plant/Plants",
    "packagingdetails": "10pcs/small polybag, 100Pcs/Big Polybag",
    "brandname": "For Sony",
    "message": "Your message must be 20-2000 characters in length. Account Characters:"
}