{
    "category": "camera",
    "lens": "F-number\u00ef\u00bc\u009aF2.8 Focal Length\u00ef\u00bc\u009af=3.8mm (Approx. 21mm equivalent to 35mm film)",
    "monitorscreen": "\u00e3\u0080\u0090Controller\u00e3\u0080\u00912.0-inch TFT color LCD, 230,400 dots, Capacitance touch panel",
    "shuttertype": "CMOS electronic shutter",
    "zoomratio": "4x digital zoom",
    "whitebalance": "Auto WB / Outdoor / Indoor",
    "fileformat": "Still images\u00ef\u00bc\u009aJPEG(Exif Ver. 2.3 / DCF2.0) Movies\u00ef\u00bc\u009aMOV format, H.264/AVC, IMA-ADPCM(monaural)",
    "sensitivity": "Still Images\u00ef\u00bc\u009aAuto Movies\u00ef\u00bc\u009aAuto",
    "wevemadeafewchangestobidding": "Were these helpful?",
    "focusrangefromlenssurface": "Auto focus\u00ef\u00bc\u009aApprox. 10 cm - Infinity",
    "selftimer": "5 seconds",
    "aperture": "F2.8",
    "timekeepingfunctions": "Date and Time\u00ef\u00bc\u009aRecorded with image data Auto Calendar\u00ef\u00bc\u009aTo 2049",
    "numberofrecordedpixels": "Still images\u00ef\u00bc\u009a14M(4320 x 3240) 16:9(4320 x 2432) 5M(2560 x 1920) Movies\u00ef\u00bc\u009aFull HD(1920 x 1080)",
    "focusing": "Focus Type\u00ef\u00bc\u009aContrast Detection Auto Focus Focus Mode\u00ef\u00bc\u009aAuto Focus AF Area\u00ef\u00bc\u009aIntelligent, Multi",
    "exposure": "Exposur Control\u00ef\u00bc\u009aProgram AE Exposure Compensation\u00ef\u00bc\u009a-2EV to +2EV (in 1/3EV steps)",
    "imagesensor": "1/2.3-inch CMOS(back-illuminated type) Total Pixels\u00ef\u00bc\u009a16.76 megapixels(/million)",
    "numberofeffectivepixels": "Approx. 14.0 megapixels"
}