{
    "category": "camera",
    "service": "(888) 473-2491",
    "label0": "Mode select transmission",
    "label1": "Radio data system",
    "label2": "Variable valve control",
    "label4": "Manual-shift auto",
    "label5": "Sequential multi-point fuel injection",
    "label6": "Rear seat center armrest",
    "label7": "Block heater",
    "bodystyle": "Truck Crew Cab",
    "parts": "(888) 475-3956",
    "compressionratio": "16.50 to 1",
    "label12": "Variable intake manifold",
    "model": "2500",
    "label15": "Limited slip differential",
    "stock": "48051"
}