{
    "category": "camera",
    "imagingelement": "About 22.3 \u00c3\u0097 14.9mm",
    "viewfindermagnification": "0.87 times",
    "color": "White",
    "shutterspeed": "(May become slower than 1/60 seconds \u00e2\u0080\u00bb wide-angle lens is used) 1 / 4000-1 / 60 seconds (Scene Intelligent Auto mode), maximum flash synchro shutter speed = 1/200 sec 1 / 4000-30 seconds , (together the all shooting modes) valve",
    "afpoint": "9 points",
    "wifi": "None",
    "focallength": "40 mm",
    "accessories": "(CD-ROM), software instructions Battery Pack LP-E12, Battery Charger LC-E12, interface cable, Wide Strap EW-200DG, EOS DIGITAL Solution Disk, the camera's Instruction Manual (CD-ROM)",
    "effectivepixels": "About 18 million pixels",
    "screensize": "3 in.",
    "storagemedia": "SD / SDHC / SDXC card \u00e2\u0080\u00bb UHS-I compatible",
    "lensmount": "Canon EF",
    "batterytype": "Richiimuion battery"
}