{
    "weight": "4.44 Oz (126 g)",
    "height": "2.44 in (62 mm)",
    "displaytype": "LCD",
    "additionalfeatures": "Not Interchangeable Lenses, USB 2.0",
    "displaysize": "2.7\" (68.6 mm)",
    "maxvideoresolution": "1280 x 720",
    "category": "camera",
    "depth": "1.07 in (27.2 mm)",
    "width": "3.76 in (95.5 mm)",
    "brand": "Panasonic",
    "sensortype": "CCD",
    "brandpanasonic": "Screen Size: 2.7\"",
    "screensize": "2.7\" (68.6 mm)",
    "integratedmemorysize": "10 MB",
    "cameratype": "Point & Shoot",
    "upc": "885170065147",
    "opticalzoom": "5x",
    "digitalzoom": "4x",
    "sensorresolution": "14.1 MP",
    "supportedflashmemory": "Built-in, SD Card, SD Memory Card, SDHC Card, SDHC Memory Card, SDXC Card, SDXC Memory Card",
    "model": "DMC-LS5"
}