{
    "productwithoutbatteryandcard": "0.48 lb.",
    "includedlens": "EX-S2050BNB/US",
    "isoequivalent": "Auto, 100, 200, 400, 800, 1600, 3200, 6400, 12800 (1 or 1/3EV step) * AUTO ISO Upper Level is Selectable. (Up to ISO3200)",
    "fieldofview": "Approx. 100%",
    "totalpixel": "Approx. 21.6 Mega-pixels",
    "powersource": "Rechargeable Battery",
    "smartfilterstillimage": "Miniature, Soft Focus, Old Film1, Old Film2,, Halftone Dots, Sketch, Fish-Eye, De-fog Negative",
    "syncspeed": "Less than 1/180 sec.",
    "productsizewxhxd": "4.59\" x 2.46\" x 1.44\"",
    "mainlcdscreen": "3\" TFT LCD",
    "category": "camera",
    "opticalimagestabilization": "OIS Mode1 / Mode2 / OFF",
    "dustreduction": "Type: Supersonic drive",
    "temperature": "0 ~ 40 \u00b0C",
    "effectivepixel": "Approx. 20.3 Mega-pixels",
    "battery": "BP1030 (1030mAh)",
    "movieclip": "With Audio or without Audio (User Selectable, Recording Time : 25 minutes)",
    "type": "20-50mm F/3.5-5.6 ED Lens (Black) EX-S2050BNB/US",
    "ieffect": "i-Scene (depends on Lens) Smart Filter (Vignetting, Minature, Fish-Eye, Sketch, Defog, Halftone Dot)",
    "picturewizard": "Modes : Standard, Vivid, Portrait, Landscape, Forest, Retro, Cool, Calm, Classic, Custom (1~3) Parameters: Contrast, Sharpness, Saturation, Color",
    "imagesize": "20.0M RAW 53 20.0M (3:2) : Super Fine 186, Fine 364, Normal 535 10.1M (3:2) : Super Fine 378, Fine 724, Normal 1043 5.9M (3:2) : Super Fine 626, Fine 1168, Normal 1642 2.0M (3:2) : Super Fine 1627, Fine 2742, Normal 3553 Burst (5.0M) : Super Fine 731, Fine 1349, Normal 1878 7.8M (16:9) : Super Fine 485, Fine 919, Normal 1310 4.9M (16:9) : Super Fine 747, Fine 1376, Normal 1912 2.1M (16:9) : Super Fine 1573, Fine 2666, Normal 3468 13.3M (1:1) : Super Fine 289, Fine 560, Normal 814 7.0M (1:1) : Super Fine 536, Fine 1010, Normal 1432 4.0M (1:1) : Super Fine 893, Fine 1621, Normal 2224 1.1M (1:1) : Super Fine 2645, Fine 4057, Normal 4936",
    "accessory": "Samsung External Flash Available (SEF-42A, SEF220A : Optional)",
    "meteringsystem": "TTL 221(17x13) Block Segment Metering : Multi, Center-weighted, Spot Metering Range : EV 0-18 (ISO 100 30mm, F2)",
    "smartauto": "2.0",
    "included": "NX1000 20.3 SMART Camera (Black) 20-50mm F/3.5-5.6 ED Lens (Black) SEF-8A Hot Shoe Mount Flash Unit BP1030 Lithium-ion Battery BC1030 Battery Charger & AC Cable Body Cap Camera Strap Micro USB Cable",
    "color": "Black",
    "videoout": "NTSC, PAL (user selectable) HDMI 1.4a : (1080i, 720P, 576P / 480P)",
    "smartfiltermovie": "Vignetting, Miniature, Fish-Eye, Sketch, De-fog, Halftone Dots, Soft Focus,Old Film1, Old Film2, Negative",
    "modes": "Auto, Daylight, Cloudy, Fluorescent (W, N, D), Tungsten, Flash, Custom, K(Manual)",
    "imagesensortype": "CMOS",
    "cameratype": "Mirrorless Interchangeable Lens",
    "windows": "PC with processor better than Intel Pentium III 500MHz (Intel Pentium 800MHz or higher recommended) Windows XP / Vista / 7 Minimum 256MB RAM (512MB or more recommended) 250MB of available hard disk space (1GB or more recommended) USB port,CD-ROM drive 1024x768 pixels, 16-bit color display compatible monitor (24-bit color display recommended) Microsoft Direct X 9.0c or later intelli-studio 3.0 Windows XP SP2 / Vista / 7 Intel Core 2 Duo 1.66 GHz or higher / AMD AthlonTM X2 Dual-Core 2.2 GHz or higher Minimum 512MB RAM (1GB or more recommended) 250MB of available hard disk space (1GB or more recommended) 1024x768 pixels, 16-bit color display compatible monitor (1280x1024 pixcels, 32-bit color display recommended) USB 2.0, Microsoft DirectX 9.0c or later nVIDIA Geforce 7600GT or higher / ATI X1600 series or higher # 64-bit editions of Windows XP / Vista / and 7 are not supported Samsung RAW converter 4 Windows XP / Vista / 7 Intel Pentium, AMD Athlon Processor (Intel Pentium 4, AMD Athlon XP or later recommended) 1GB or more RAM recommended Minimum 100MB of available hard disk space 1024x768 pixels, Full Color (24-bit or higher) color display compatible monitor",
    "izoom": "x1.2, 1.4, 1.7, 2.0",
    "mount": "Samsung NX mount",
    "wifi": "Yes (IEEE 802.11n support)",
    "humidity": "5 ~ 85%",
    "range": "28mm Wide-angle (Equivalent to 35mm)",
    "usb20": "USB 2.0 (HI-SPEED)",
    "resolution": "8VGA ( 640X40 ) 921k dots",
    "fileformat": "RAW (SRW), JPEG (EXIF 2.21), DCF, DPOF 1.1, PictBridge 1.0",
    "macintosh": "Power Mac G3 or later Mac OS 10.4 or later Minimum 256MB RAM (512MB or more recommended) Minimum 110MB of available hard-disk space USB port,CD-ROM drive Samsung RAW converter 4 Mac OS X v10.6 / v10.5 / v10.4 Power PC / Intel Processor-based or compatible computer (Core 2 Quad or later recommended) 1GB or more RAM recommended Minimum 100MB of available hard disk space 1024x768 pixels, 24-bit color display compatible monitor"
}