{
    "videocapability": "Y",
    "pictbridge": "Y",
    "lightexposurecontrol": "Program AE",
    "colourofproduct": "Black",
    "weight": "515g",
    "lightexposuremodes": "Aperture priority AE, Auto, Manual, Shutter priority AE",
    "isosensitivity": "100, 125, 160, 200, 250, 320, 400, 500, 640, 800, 1000, 1250, 1600, 2000, 2250, 2500, 3200, 4000, 5000, 6400",
    "stillimageresolutions": "720 x 480, 1920 x 1280, 2592 x 1728, 3456 x 2304, 5184 x 3456",
    "focus": "TTL",
    "onscreendisplayosdlanguages": "ARA, CHI (SIMPL), CHI (TR), CZE, DAN, DEU, DUT, ENG, ESP, FIN, FRE, GRE, HUN, ITA, JPN, KOR, NOR, POL, POR, RUM, RUS, SWE, THA, TUR, UKR",
    "height": "9.95 cm",
    "autofocusaflock": "Y",
    "maccompatibility": "Y",
    "camerashutterspeedmax": "0.00025s",
    "flashexposurelock": "Y",
    "operatingtemperaturett": "0 - 40 \u00b0C 32 - 104 \u00b0F",
    "tripodmountable": "Y",
    "displaydiagonal": "7.62 cm (3\")",
    "batterytype": "LP-E8",
    "flashguidenumber": "13m",
    "shootingmodes": "Aperture priority, Auto, Manual, Movie, Shutter priority",
    "category": "camera",
    "totalmegapixels": "18.7 MP",
    "lightexposurecorrection": "\u00b1 5EV (1/3EV step)",
    "startuptime": "100 ms",
    "motionjpegframerate": "30 fps",
    "macoperatingsystemssupported": "Mac OS X 10.5 Leopard, Mac OS X 10.6 Snow Leopard",
    "lightmetering": "Centre-weighted, Spot",
    "autofocusafassistbeam": "Y",
    "usb20portsquantity": "1",
    "selftimer": "2, 10s",
    "width": "13.31 cm",
    "magnification": "0.85x",
    "supportedaspectratios": "3:2",
    "windowsoperatingsystemssupported": "Windows 7 Home Premium, Windows 7 Home Premium x64, Windows 7 Professional, Windows 7 Professional x64, Windows 7 Starter, Windows 7 Starter x64, Windows 7 Ultimate, Windows 7 Ultimate x64, Windows Vista Business, Windows Vista Business x64, Windows Vista Home Basic, Windows Vista Home Basic x64, Windows Vista Home Premium, Windows Vista Home Premium x64, Windows Vista Ultimate, Windows Vista Ultimate x64, Windows XP Home, Windows XP Home x64, Windows XP Professional, Windows XP Professional x64",
    "flashmodes": "Auto, Flash off, Manual",
    "flashexposurecompensation": "Y",
    "digitalslr": "Y",
    "cameraplayback": "Movie, Single image",
    "maximumvideoresolution": "1920 x 1080 pixels",
    "type": "digital cameras",
    "flashsyncspeed": "0.005s",
    "videoformatssupported": "H.264, MOV",
    "camerafilesystem": "Exif 2.3",
    "histogram": "Y",
    "fieldofview": "100%",
    "hdmiportsquantity": "1",
    "batteriesincluded": "Y",
    "isosensitivitymin": "100",
    "brand": "Canon",
    "whitebalance": "Auto, Cloudy, Custom modes, Daylight, Fluorescent, Shade, Tungsten",
    "autofocusingafmodes": "Single Auto Focus",
    "sensortype": "CMOS",
    "batterychargerincluded": "Y",
    "scenemodes": "Landscape, Portrait",
    "part": "5169B001",
    "batterylifecipastandard": "400 shots",
    "fullhd": "Y",
    "interface": "USB 2.0",
    "powersourcetype": "Battery",
    "operatingrelativehumidityhh": "0 - 85%",
    "flashrechargingtime": "3s",
    "displayresolutionnumeric": "1040000 pixels",
    "analogsignalformatsystem": "NTSC, PAL",
    "released": "2011-05-18",
    "externalflashconnector": "Y",
    "camerashuttertype": "Electronic",
    "camerashutterspeedmin": "30s",
    "cameratype": "SLR Body",
    "batterytechnology": "Lithium-Ion (Li-Ion)",
    "compatiblememorycards": "SD, SDHC, SDXC",
    "flashexposurecorrection": "\u00b12EV (1/2, 1/3 EV step)",
    "isosensitivitymax": "6400",
    "megapixel": "18 MP",
    "depth": "7.97 cm",
    "directprinting": "Y",
    "builtinflash": "Y",
    "videoresolutions": "640 x 480, 1280 x 720, 1920 x 1080 pixels",
    "autoexposureaelock": "Y",
    "display": "LCD",
    "maximumimageresolution": "5184 x 3456 pixels"
}