{
    "selftimerdelay": "2s / 10s",
    "weight": "148 g",
    "flashtype": "Built-in",
    "battery": "Li-Ion",
    "height": "59 mm",
    "exposurecompensation": "-/+ 2 EV range, in 1/3 EV steps",
    "userreviews": "Write a review",
    "screentype": "LCD",
    "whitebalancepresets": "Cloudy / Daylight / Sunny / Fluorescent / Incandescent / Tungsten",
    "installedmemory": "30 MB",
    "microphone": "Yes",
    "specialeffects": "Contrast / Custom Effect / Fisheye / Retro / Saturation / Soft Focus / Vivid",
    "includedaccessories": "AV cable / Carrying strap / Charger / USB cable",
    "lightsensitivityiso": "Auto / 80 / 100 / 200 / 400 / 800 / 1600 / 3200",
    "redeyereduction": "Yes",
    "depth": "20 mm",
    "sensorsize": "1/2.3",
    "width": "100 mm",
    "resolution": "14 MP (more than 67%)",
    "meteringmodes": "Center-weighted / Multi / Spot",
    "aperture": "F/3.3-5.9",
    "category": "camera",
    "minshutterspeed": "8s",
    "imageresolutions": "640x480 / 1024x768 / 1280x1024 / 1920x1080 / 2592x1944 / 3648x2736 / 4320x2432 / 4320x2880 / 4320x3240 / 4608x2592 / 4608x3072 / 4608x3456",
    "flashrange": "3.30 m",
    "focallength": "4.85 - 48.5 mm",
    "brand": "Samsung",
    "imagestabilizer": "Optical",
    "sensortype": "CCD",
    "ean": "8806071328409, 8806071191942, 0610563291809, 0610563291823, 8806071202051, 0610563291793, 0876544738446, 0876544738439, 8806071223575, 0044701015604, 8806071420349, 0044701015598, 0610563291816",
    "memorytype": "SD / SDHC / SDXC / micro SD / micro SDHC",
    "screensize": "3\" (more than 62%)",
    "digitalvideoformat": "AVI / MJPEG / MPEG / WAV / H.264",
    "displayformfactor": "Fixed",
    "screenresolution": "230000",
    "imageprocessor": "Prime",
    "lowestprice": "Rs.10,900 Show all prices \u00bb",
    "productrating": "0 out of 5",
    "bodytype": "Ultracompact",
    "flashmodes": "Auto / Fill-in / Manual / Off / Red Eye Reduction / Slow Speed Sync",
    "connectortype": "Composite / HDMI / USB",
    "exposuremodes": "Auto / Custom / Manual / Program / Scene",
    "upc": "610563291809, 610563291823, 610563291793, 876544738446, 876544738439, 044701015604, 044701015598, 610563291816",
    "opticalzoom": "10x (more than 83%)",
    "productname": "Samsung PL210",
    "digitalzoom": "5x",
    "maxshutterspeed": "1/2000",
    "recordingfunctions": "Face Detection",
    "videoresolution": "320x240 / 1280x720",
    "whitebalance": "Automatic / Custom / Presets",
    "imageformat": "DCF / DPOF / JPEG"
}