{
    "selftimerdelay": "2s / 10s",
    "weight": "183 g",
    "productrating": "0 out of 5",
    "battery": "Li-Ion",
    "height": "68 mm",
    "exposurecompensation": "-/+ 2 EV range, in 1/3 EV steps",
    "environmentallysealed": "Dustproof / Shockproof / Waterproof",
    "opticalzoom": "5x (more than 61%)",
    "whitebalancepresets": "Fluorescent / Incandescent / Shade / Underwater",
    "installedmemory": "95 MB",
    "microphone": "Yes",
    "includedaccessories": "Carrying strap / Power adapter / USB cable",
    "width": "99 mm",
    "lightsensitivityiso": "Auto / 100 / 200",
    "depth": "26 mm",
    "sensorsize": "1/2.3",
    "liveview": "Yes",
    "meteringmodes": "Multi",
    "aperture": "F/3.9-4.9",
    "autofocus": "Center  / Continuous  / Contrast Detect  / Single  / Tracking",
    "lowestrecommendedprice": "Rs.16,577 - Grabmore  India Show all prices \u00bb",
    "category": "camera",
    "userreviews": "Write a review",
    "imageresolutions": "1920x1080 / 2048x1536 / 3264x1836 / 3264x2448 / 3456x3456 / 4608x2592 / 4608x3072 / 4608x3456",
    "ean": "0845251051018, 0074101021509, 0074101021479, 0074101021462, 0845251050998, 4547410240412, 4547410240504, 4547410240443",
    "brand": "Fujifilm",
    "sensortype": "CMOS",
    "afilluminator": "Yes",
    "memorytype": "SD / SDHC / SDXC",
    "screensize": "2.7\"",
    "digitalvideoformat": "MOV / H.264",
    "displayformfactor": "Fixed",
    "screenresolution": "230000",
    "continuousshootingspeed": "70",
    "bodytype": "Compact",
    "flashmodes": "Auto / Off / On",
    "connectortype": "USB / micro HDMI",
    "upc": "845251051018, 074101021509, 074101021479, 074101021462, 845251050998",
    "screentype": "LCD",
    "productname": "Fujifilm FinePix XP60",
    "digitalzoom": "2x",
    "recordingfunctions": "Face Detection  / HDR  / Sweep Panorama",
    "resolution": "16 MP (more than 78%)",
    "focallengthequivalentto35mm": "28 - 140 mm",
    "imageformat": "DPOF / JPEG / MPO"
}