{
    "ledindicators": "Power, Link, ACT",
    "weight": "800g (1.8 pounds)",
    "electronicshutterspeed": "1~ 1/10,000 sec",
    "connections": "RJ-45 10BASE-T/100BASE-TX, 3.5 mm Speaker, 3.5mm MIC, DC Power jack, AC power terminal block, BNC analog video output",
    "pantiltzoom": "3-axis Manual Pan/Tilt, Digital 16x Zoom",
    "localstorage": "Micro SDHC slot",
    "operatingsystem": "Microsoft Windows 2000/XP/Vista/7",
    "category": "camera",
    "dimensions": "151mm dia x 130mm (5.9\" dia x 5.1\")",
    "housing": "Vandal-proof: Metal base and polycarbonate transparent cover, weather-proof IP66-rated housing",
    "motiondetection": "2 Detection Areas with individual sensitivity",
    "powerrequirements": "12VDC, 24VAC, PoE 5.5W",
    "memory": "128MB Flash ROM, 128MB RAM",
    "numberofclients": "20",
    "picture": "JPEG",
    "approvals": "CE, FCC",
    "lens": "Vari-Focus board lens, F 1.4 / f=3.3~12 mm",
    "videocompression": "H.264 & MJPEG",
    "webbrowser": "IE 6.0 or above",
    "protocols": "IPv4, TCP/IP, UDP, RTP, RTSP, HTTP, ICMP,FTP, SMTP, DHCP, PPPoE, UPnP and IGMP",
    "manufacturer": "Level One",
    "operatingtemperature": "-10\u00b0C ~ 50\u00b0C (14\u00b0F ~ 122\u00b0F)",
    "minillumination": "Color 0.2 lux, B&W 0.02 lux @ F1.4",
    "operatinghumidity": "10% ~ 90%",
    "imagesensor": "1/2.5\" CMOS 2-Megapixel Progressive",
    "audiocompression": "G.711, G.726",
    "upc": "846359002810",
    "ethernet": "10BASE-T / 100BASE-TX (RJ-45)",
    "security": "Multi-level user access with password protection",
    "audio": "2-Way Audio, external Mic input, external speaker output"
}