{
    "warrantyinformation": "1 Year",
    "wideangle": "Yes",
    "minimumdiopteradjustment": "No",
    "imagestabilization": "Optical",
    "weight": "4.37 oz",
    "pictbridge": "Yes",
    "isosensitivity": "ISO 6400",
    "focallength": "4.30 mm to 51.60 mm",
    "longestshutterspeed": "8 Second",
    "height": "2.2 in",
    "label18": "Additional Specifications",
    "label50": "Quick Glance",
    "label10": "Dimensions",
    "productseries": "T",
    "normalizeddigitalzoom": "2",
    "batterymodelsupported": "NP-45A / NP-45B",
    "label15": "Reference",
    "cameramodes": "Shooting Modes",
    "productline": "FinePix",
    "batterybuiltin": "No",
    "flash": "Auto Flash|Flash OFF|Flash ON|Suppressed Flash|Slow Sync|Red-eye Reduction",
    "digitalzoom": "2x",
    "shortestshutterspeed": "1/2000 Second",
    "width": "3.9 in",
    "maximumframerate": "30 fps",
    "normalizedopticalzoom": "12",
    "whitebalancemodes": "Automatic Scene RecognitionFineShadeFluorescent Light (Daylight)Fluorescent Light (Warm White)Fluorescent Light (Cool White)Incandescent Light",
    "gps": "No",
    "category": "camera",
    "maximumvideocaptureresolution": "1280 x 720",
    "batteryrechargeable": "Yes",
    "label0": "Quick Glance",
    "memorycardsupport": "Secure Digital (SD) Card|Secure Digital High Capacity (SDHC) Card|Secure Digital Extended Capacity (SDXC)",
    "label2": "Other Features",
    "lensconstruction": "9 Elements in 9 Groups",
    "parentproducttype": "Digital Camera",
    "label5": "Lens Features",
    "greencompliance": "REACH|WEEE",
    "numberofbatteriessupport": "1",
    "brandname": "Fujifilm",
    "normalizedweight": "4.37",
    "maximumdiopteradjustment": "No",
    "focallength35mmequivalent": "24 mm to 288 mm",
    "cameratype": "Compact Camera",
    "productmodel": "T550",
    "builtinflash": "Yes",
    "hdmoviemode": "Yes",
    "opticalzoom": "12 X",
    "lcdscreensize": "3 in",
    "exposurecontrol": "Program AE",
    "depth": "1.0 in",
    "viewfindertype": "No",
    "effectivemegapixels": "16 Megapixel",
    "batteryinclude": "Yes",
    "imagesensor": "CCD"
}