{
    "Sensitivity": "118dB",
    "Nominal Impedance": " 18 Ohms",
    "Cord Length": " 4 ft (1.3 m.)",
    "Cable Type": " Flat",
    "Plug Size": " 1/8\" (3.5xmm)",
    "Weight/Mass": " 0.56 oz (16g)",
    "Pick-up Pattern": " Omni-Directional",
    "Condition": "New: A brand-new, unused, unopened, undamaged item in its original packaging (where packaging is applicable). Packaging should be the same as what is found in a retail store, unless the item is handmade or was packaged by the manufacturer in non-retail packaging, such as an unprinted box or plastic bag. See the seller's listing for full details. See all condition definitions- opens in a new window or tab ... Read moreabout the condition",
    "Brand": "Sennheiser",
    "MPN": "100227",
    "Earpiece Design": "Earbud (In Ear)",
    "Model": "M2 IEi",
    "Fit Design": "In-Ear Only",
    "Color": "Black/Red",
    "UPC": "615104270350"
}