{
    "macrofocusrange": "10-70cm",
    "weight": "4 Oz.",
    "flashtype": "Built-in flash",
    "maxoperatingtemperature": "40 \u00c2\u00b0C",
    "height": "2.2 in.",
    "displaytype": "LCD",
    "additionalfeatures": "Audio Recording, Automatic Face Tracking, Automatic Scene Recognition (SR Auto), Cropping An Image, Digital Image Rotation, Exif Print Support, Face Detection, Not Interchangeable Lenses, Panorama Preview, PictBridge Support, Red eye Fix, Red-eye Correction, USB 2.0, USB 2.0 Compatibility",
    "connectortypes": "1 x USB",
    "flashmodes": "Auto Mode, Fill-in Mode, OFF mode, Red-eye Reduction, Slow Synchro",
    "maxvideoresolution": "640 x 480 (VGA)",
    "category": "camera",
    "displayrotation": "Built-in",
    "lightsensitivitymax": "3200",
    "stillimageformat": "EXIF 2.2, JPEG",
    "screendetails": "LCD display - TFT active matrix - 3\" - color",
    "redeyereduction": "Yes",
    "lightsensitivity": "ISO 100, ISO 1600, ISO 200, ISO 3200 (3Mpix), ISO 400, ISO 800, ISO auto",
    "sensorsize": "1/2.3\"",
    "width": "3.62 in.",
    "autofocustype": "TTL contrast detection",
    "digitalzoom": "6x",
    "focallengthequivalentto35mmcamera": "32 - 96mm",
    "minshutterspeed": "8 sec",
    "batteryformfactor": "Manufacturer specific",
    "mpn": "J40",
    "brand": "Fujifilm",
    "continuousshootingspeed": "30 frames per second",
    "minoperatingtemperature": "0 \u00c2\u00b0C",
    "screensize": "3\"",
    "microphoneoperationmode": "Mono",
    "microphonetype": "Microphone - built-in - electret condenser - mono",
    "integratedmemorysize": "12 MB",
    "expansionslot": "1 x SD Memory Card",
    "focusadjustment": "Automatic",
    "cameratype": "Point & Shoot",
    "shootingmodes": "Frame Movie Mode",
    "maxshutterspeed": "1/1400 sec",
    "exposuremodes": "Automatic, Program",
    "upc": "74101005745",
    "opticalzoom": "3x",
    "displaysize": "3\"",
    "depth": "0.79 in.",
    "sensorresolution": "12.2 MP",
    "viewfindertype": "None",
    "sensortype": "CCD",
    "supportedflashmemory": "SD Card, SD Memory Card, SDHC Card, SDHC Memory Card",
    "model": "J40",
    "shootingprograms": "Anti shake, Baby, Beach, Fireworks, Flower, Landscape, Natural light, Night (tripod), Night mode, Panorama assist, Party/indoor, Portrait mode, Snow, Sports mode, Sunset, Text",
    "whitebalance": "Fluorescent (Preset), Incandescent (Preset), Shade (Preset)"
}