{
    "category": "camera",
    "angleofview": "107\u00b0\u00a030' - 74\u00b0\u00a020'",
    "weight": "8.47 oz (240 g)",
    "minimumfocusdistance": "8.66\"\u00a0(22 cm)",
    "dimensionsdxl": "Approx. 2.94 x 2.83\" (74.6 x 72 mm)",
    "focallength": "10 - 18mm",
    "filterthread": "Front:67 mm",
    "formatcompatibility": "Canon (APS-C)",
    "magnification": "0.15x",
    "diaphragmblades": "7, Rounded",
    "elementsgroups": "14/11",
    "imagestabilization": "Yes",
    "aperture": "Maximum: f/4.5 - 5.6",
    "autofocus": "Yes",
    "cameramounttype": "Canon EF-S"
}