{
    "externalflashconnection": "Hot Shoe, PC Terminal, Proprietary, Wireless",
    "weight": "1.09 lb\u00a0/\u00a0497 g\u00a0CIPA guideline compliant, with battery and memory card",
    "maxsyncspeed": "1 / 320 sec",
    "battery": "1x BLN-1\u00a0 Rechargeable Lithium-Ion Battery Pack, 7.6VDC, 1220mAh",
    "isosensitivity": "Auto, 100-25600",
    "memorycardtype": "SD",
    "viewfinderpixelcount": "2,360,000",
    "imagestabilization": "Sensor-Shift, 5-Way",
    "lensmount": "Micro Four Thirds",
    "viewfindercoverage": "100%",
    "category": "camera",
    "shutter": "Type: Electronic & Mechanical",
    "videorecording": "Yes, NTSC/PAL",
    "burstrate": "Up to 10 fps",
    "operatingstoragetemperature": "Operating",
    "viewfindereyepoint": "21.00 mm",
    "fileformats": "Still Images:\u00a0JPEG, MPO, RAW",
    "selftimer": "12 sec, 2 sec",
    "dimensionswxhxd": "5.1 x 3.7 x 2.5\"\u00a0/\u00a0130.4 x 93.5 x 63.1 mm\u00a0CIPA guideline compliant, excluding protrusions",
    "continuousshooting": "Up to 10 fps",
    "meteringmethod": "Center-weighted average metering, Multi-zone metering, Spot metering",
    "audiorecording": "Built-in Mic: With Still Images & Video, Stereo",
    "whitebalancemodes": "Auto, Cloudy, Custom, Flash, Fluorescent, Incandescent, Kelvin, Shade, Sunlight, Underwater",
    "dustreductionsystem": "Yes",
    "viewfindermagnification": "Approx. 1.48x",
    "flashcompensation": "-3 EV to +3 EV (in 1/3, 1/2 or 1 EV steps)",
    "sensortypesize": "MOS, 17.3 x 13 mm",
    "connectivity": "USB 2.0",
    "cameraformat": "Micro Four Thirds (2x Crop Factor)",
    "focustype": "Auto & Manual",
    "bitdepth": "12-bit",
    "aspectratio": "4:3, 16:9",
    "displayscreen": "3\"\u00a0Wide Touchscreen\u00a0Tilting\u00a0\u00a0LCD (1,037,000)",
    "pixels": "Actual: 16.8 Megapixel",
    "screencoverage": "100%",
    "intervalrecording": "Yes",
    "remotecontrol": "RM-UC1 (Optional)",
    "diopteradjustment": "- 4 to +2 m",
    "flashmodes": "Auto",
    "builtinflash": "No",
    "exposuremodes": "Modes: Aperture Priority, Art Filter, Bulb, Manual, Programmed Auto, Scene Selection, Shutter Priority, Time, Underwater, iAUTO",
    "focusmode": "Single-servo AF (S), Continuous-servo AF (C), Manual Focus (M)",
    "videocliplength": "Up to 29\u00a0Min",
    "viewfindertype": "Electronic",
    "autofocuspoints": "Contrast Detection: 81",
    "dedicatedflashsystem": "TTL Groups: 4 Channels: 4",
    "maxresolution": "15.9MP: 4608 x 3456",
    "resolution": "1920 x 1080: 30 fps",
    "wificapable": "Yes"
}