{
    "weight": "1000g",
    "shuttertime": "1/25(1/30) s to 1/100,000 s",
    "powerconsumption": "Max. 5.5 W",
    "framerate": "50 Hz: 25 fps (1280 \u00d7 960), 25 fps (1280 x 720), 25 fps (704 x 576), 25 fps (640 x 480) 60 Hz: 30 fps (1280 \u00d7 960), 30 fps (1280 x 720), 30 fps (704 x 576), 30 fps (640 x 480)",
    "image": "Max. Image Resolution: 1280x960 Frame Rate: 50 Hz: 25 fps (1280 \u00d7 960), 25 fps (1280 x 720), 25 fps (704 x 576), 25 fps (640 x 480) 60 Hz: 30 fps (1280 \u00d7 960), 30 fps (1280 x 720), 30 fps (704 x 576), 30 fps (640 x 480) Image Settings: Saturation, brightness, contrast adjustable through client software or web browser BLC: Yes, zone configurable",
    "powersupply": "12 VDC \u00b1 10%, PoE (802.3af)",
    "general": "Operating Conditions: -30 \u00b0C ~ 60 \u00b0C (-22 \u00b0F ~ 140 \u00b0F) Humidity 95% or less (non-condensing) Power Supply: 12 VDC \u00b1 10%, PoE (802.3af) Power Consumption: Max. 5.5 W Impact Protection: IEC60068-2-75Eh, 50J; EN50102, up to IK10 Weather Proof: IP66 IR Range: Up to 20m Dimensions: \u03a6 140 \u00d7 99.9 mm (\u03a6 5.51\u201d \u00d7 3.94\u201d) Weight: 1000g",
    "weatherproof": "IP66",
    "widedynamicrange": "Digital WDR",
    "onboardstorage": "Built-in Micro SD/SDHC/SDXC card slot, up to 64 GB",
    "imagesettings": "Saturation, brightness, contrast adjustable through client software or web browser",
    "digitalnoisereduction": "3D DNR",
    "operatingconditions": "-30 \u00b0C ~ 60 \u00b0C (-22 \u00b0F ~ 140 \u00b0F) Humidity 95% or less (non-condensing)",
    "communicationinterface": "1 RJ45 10M / 100M ethernet interface",
    "network": "Network Storage: NAS Alarm Trigger: Motion detection, Dynamic Analysis, Tampering alarm, Network disconnect, IP address conflict, Storage exception Protocols: TCP/IP,ICMP,HTTP,HTTPS,FTP,DHCP,DNS,DDNS,RTP,RTSP,RTCP, PPPoE,NTP,UPnP,SMTP,SNMP,IGMP,802.1X,QoS,IPv6,Bonjour Security: User authentication, watermark System Compatibility: ONVIF, PSIA, CGI, ISAPI",
    "alarmtrigger": "Motion detection, Dynamic Analysis, Tampering alarm, Network disconnect, IP address conflict, Storage exception",
    "port": "shenzhen",
    "fobprice": "Get Latest Price",
    "dualstream": "Yes",
    "camera": "Image Sensor: 1/3\" Progressive Scan CMOS Signal System: PAL/NTSC Min. Illumination: 0.01lux @(F1.2,AGC ON) ,0 Lux with IR 0.014lux @(F1.4,AGC ON), 0 Lux with IR Shutter time: 1/25(1/30) s to 1/100,000 s Lens: 2.8 - 12 mm @ F1.4,Angle of view: 80\u00b0-28.7\u00b0 Lens Mount: \u03c614 Adjustment Range: Pan:0\u00b0 - 355\u00b0, Tilt: 0\u00b0 - 75\u00b0, Rotation: 0\u00b0 - 355\u00b0 Day& Night: IR cut filter with auto switch Wide Dynamic Range: Digital WDR Digital noise reduction: 3D DNR",
    "daynight": "IR cut filter with auto switch",
    "blc": "Yes, zone configurable",
    "networkstorage": "NAS",
    "category": "camera",
    "paymentterms": "Western Union,Paypal,Escrow",
    "supplyability": "5000 Piece/Pieces per   Month",
    "impactprotection": "IEC60068-2-75Eh, 50J; EN50102, up to IK10",
    "resetbutton": "Yes",
    "lens": "2.8 - 12 mm @ F1.4,Angle of view: 80\u00b0-28.7\u00b0",
    "videocompression": "H.264/M-JPEG",
    "signalsystem": "PAL/NTSC",
    "adjustmentrange": "Pan:0\u00b0 - 355\u00b0, Tilt: 0\u00b0 - 75\u00b0, Rotation: 0\u00b0 - 355\u00b0",
    "interface": "Communication Interface: 1 RJ45 10M / 100M ethernet interface On-board storage: Built-in Micro SD/SDHC/SDXC card slot, up to 64 GB Reset Button: Yes",
    "lensmount": "\u03c614",
    "bitrate": "32 Kbps ~ 16 Mbps",
    "protocols": "TCP/IP,ICMP,HTTP,HTTPS,FTP,DHCP,DNS,DDNS,RTP,RTSP,RTCP, PPPoE,NTP,UPnP,SMTP,SNMP,IGMP,802.1X,QoS,IPv6,Bonjour",
    "dimensions": "\u03a6 140 \u00d7 99.9 mm (\u03a6 5.51\u201d \u00d7 3.94\u201d)",
    "minillumination": "0.01lux @(F1.2,AGC ON) ,0 Lux with IR 0.014lux @(F1.4,AGC ON), 0 Lux with IR",
    "imagesensor": "1/3\" Progressive Scan CMOS",
    "audiocompression": "-S: G.711/G.726/MP2L2",
    "systemcompatibility": "ONVIF, PSIA, CGI, ISAPI",
    "maximageresolution": "1280x960",
    "irrange": "Up to 20m",
    "security": "User authentication, watermark"
}