{
    "category": "camera",
    "function": "HI-FI MP3 + HD 720P Camera + Bluetooth",
    "batterylife": "Video recording \u2265 270 Minutes;",
    "earphone": "in-ear Hi-Fi 6u high stereo",
    "usb": "USB2.5'",
    "weight": "G.W.: 11KGS CBM=16KGS",
    "certification": "CE, FCC, ROHS",
    "powerconsumption": "<0.8W",
    "sensor": "OV CMOS 7670 sensor",
    "videoimageresolution": "1280*720P",
    "playersoftware": "Windows Media Player, Real player,Stormcodec",
    "cartonsize": "42*42*46cm",
    "externalmemorycard": "Support external Mini SD Card (Max 32GB)",
    "framematerial": "ABS+PC",
    "powersource": "650mAh battery",
    "batterytype": "Rechargeable lithium-ion polymer,charged via USB connection or optional external charger",
    "lenses": "Lens is changeable"
}