{
    "softwaremanagement": "CMS & ONVIFCompatible Devices",
    "weight": "-",
    "certification": "CE ,FCC",
    "color": "WhiteResolution::1080PMeterial::Metal",
    "steamflow": "Support dual stream",
    "accessories": "Power adapter, Network cable, Stand, Operation manual, CD, Screw bag",
    "irfilter": "IR-CUT",
    "factorylocation": "No. 405,Huafeng Xin'an Business Building, 45 Area, BaoAn Dist.ShenZhen,",
    "webbrowser": "Microsoft Internet Explorer 6.0 and above,google,firefox etc.",
    "technology": "InfraredSpecial Features:Vandal-proofCertifications::CE,FCC,UL",
    "size": "1/2.5\"",
    "category": "camera",
    "waterproofrate": "IP66Connection::wired/wirelessOnvif 2.0:Support",
    "compression": "H.264 Main Profile/Baseline",
    "numberofqcstaff": "Less than 5 People",
    "powercomsumption": "DC 12V ,Module power consumption is less than 2 W",
    "electronicshutter": "1/5-1/15,000 /S",
    "safety": "IP address filtering,User level password protection,The user access",
    "placeoforigin": "Guangdong China (Mainland)Brand Name:WINBOModel Number:SAV-CM1024V",
    "dayandnight": "Yes",
    "pictureresolution": "1280*1080@\u00a030fps",
    "aperture": "Fixed Aperture F1.2",
    "factorysizesqmeters": "1,000-3,000 square meters",
    "imageenhancement": "AWB/BLC / Brightness / Contrast/Saturation",
    "contractmanufacturing": "OEM Service Offered",
    "flipconfig": "Up/down, Left/right",
    "snratio": ">50DB",
    "lens": "4-9MM/2.8-12MM Lens optional",
    "bitratetype": "CBR/VBR",
    "devicetype": "1080P Sony MX 122 CMOS sensor",
    "irdistance": "15-20M",
    "numberofrdstaff": "11 - 20 People",
    "bitrate": "128-8192kbps",
    "audioinputoutput": "1CH Input,1CH output",
    "temperature": "-20\u00b0~60\u00b0C",
    "irled": "Yes,Day&Night",
    "mobilephone": "iPhone,Android,Blackberry",
    "subtitlesinput": "Channel name, Date/Time",
    "type": "Digital CameraStyle:Dome CameraSensor:CMOS",
    "audiocompression": "G.711 / G.726",
    "humidity": "-10~85%",
    "item": "Dome IP Camera",
    "remoteaccess": "DDNS / Software / P2P",
    "ethernet": "Ethernet (10/100 Base-T),RJ-45",
    "model": "SAV-CM1024V",
    "audio": "Microphone input and Line out/ two-way voice intercom",
    "dimension": "-",
    "software": "IP Camera Client software"
}